pixyverse/render_html/__init__.py
pixyverse/render_html/render.py
pixyverse_render_html-0.1.6.dist-info/LICENSE
pixyverse_render_html-0.1.6.dist-info/METADATA
pixyverse_render_html-0.1.6.dist-info/WHEEL
pixyverse_render_html-0.1.6.dist-info/RECORD
